github_reserved_names/__init__.py
github_reserved_names/py.typed
github_reserved_names/tests/__init__.py
github_reserved_names/tests/test_github_reserved_names.py
github_reserved_names-2025.10.1.dist-info/METADATA
github_reserved_names-2025.10.1.dist-info/WHEEL
github_reserved_names-2025.10.1.dist-info/licenses/COPYING
github_reserved_names-2025.10.1.dist-info/RECORD
