Metadata-Version: 2.4
Name: github_reserved_names
Version: 2025.10.1
Summary: A list of paths that GitHub uses which aren't real users
Project-URL: Homepage, https://github.com/Julian/github-reserved-names
Project-URL: Issues, https://github.com/Julian/github-reserved-names/issues/
Project-URL: Source, https://github.com/Julian/github-reserved-names
Author-email: Julian Berman <Julian+gh-reserved-names@GrayVines.com>
License-File: COPYING
Keywords: github,github api
Classifier: Development Status :: 5 - Production/Stable
Classifier: Intended Audience :: Developers
Classifier: License :: OSI Approved :: MIT License
Classifier: Operating System :: OS Independent
Classifier: Programming Language :: Python
Classifier: Programming Language :: Python :: 3.10
Classifier: Programming Language :: Python :: 3.11
Classifier: Programming Language :: Python :: 3.12
Classifier: Programming Language :: Python :: 3.13
Classifier: Programming Language :: Python :: 3.14
Classifier: Programming Language :: Python :: Implementation :: CPython
Classifier: Programming Language :: Python :: Implementation :: PyPy
Classifier: Typing :: Typed
Requires-Python: >=3.10
